CHANGES.txt
CONTRIBUTORS.txt
COPYRIGHT.txt
LICENSE.txt
MANIFEST.in
README.txt
setup.cfg
setup.py
collective/__init__.py
collective.groupspace.mail.egg-info/PKG-INFO
collective.groupspace.mail.egg-info/SOURCES.txt
collective.groupspace.mail.egg-info/dependency_links.txt
collective.groupspace.mail.egg-info/entry_points.txt
collective.groupspace.mail.egg-info/namespace_packages.txt
collective.groupspace.mail.egg-info/not-zip-safe
collective.groupspace.mail.egg-info/paster_plugins.txt
collective.groupspace.mail.egg-info/requires.txt
collective.groupspace.mail.egg-info/top_level.txt
collective/groupspace/__init__.py
collective/groupspace/mail/__init__.py
collective/groupspace/mail/config.py
collective/groupspace/mail/configure.zcml
collective/groupspace/mail/roles.py
collective/groupspace/mail/browser/__init__.py
collective/groupspace/mail/browser/configure.zcml
collective/groupspace/mail/browser/mailview.pt
collective/groupspace/mail/browser/mailview.py
collective/groupspace/mail/locales/collective.groupspace.mail.pot
collective/groupspace/mail/locales/en/LC_MESSAGES/collective.groupspace.mail.po
collective/groupspace/mail/locales/es/LC_MESSAGES/collective.groupspace.mail.po
collective/groupspace/mail/locales/fr/LC_MESSAGES/collective.groupspace.mail.po
collective/groupspace/mail/portlets/__init__.py
collective/groupspace/mail/portlets/configure.zcml
collective/groupspace/mail/portlets/groupmailportlet.pt
collective/groupspace/mail/portlets/groupmailportlet.py
collective/groupspace/mail/profiles/default/actions.xml
collective/groupspace/mail/profiles/default/portlets.xml
collective/groupspace/mail/profiles/default/rolemap.xml
collective/groupspace/mail/tests/__init__.py
collective/groupspace/mail/tests/base_groupmailportlet.py
collective/groupspace/mail/tests/test_groupmailportlet.py